{
  "annotations": {
    "list": [
      {
        "builtIn": 1,
        "datasource": "-- Grafana --",
        "enable": true,
        "hide": false,
        "iconColor": "rgba(0, 211, 255, 1)",
        "name": "Annotations & Alerts",
        "type": "dashboard"
      }
    ]
  },
  "editable": true,
  "fiscalYearStartMonth": 0,
  "graphTooltip": 0,
  "iteration": 0,
  "links": [],
  "panels": [
    {
      "datasource": {
        "type": "prometheus",
        "uid": "Prometheus"
      },
      "fieldConfig": {
        "defaults": {
          "color": {
            "mode": "palette-classic"
          },
          "mappings": [],
          "thresholds": {
            "mode": "absolute",
            "steps": [
              {
                "color": "green",
                "value": null
              },
              {
                "color": "red",
                "value": 80
              }
            ]
          }
        },
        "overrides": []
      },
      "gridPos": {
        "h": 8,
        "w": 12,
        "x": 0,
        "y": 0
      },
      "id": 1,
      "options": {
        "legend": {
          "calcs": [],
          "displayMode": "list",
          "placement": "bottom"
        },
        "tooltip": {
          "mode": "multi",
          "sort": "none"
        }
      },
      "targets": [
        {
          "expr": "sum(rate(axum_http_requests_total[5m])) by (status)",
          "legendFormat": "status {{status}}",
          "refId": "A"
        }
      ],
      "title": "HTTP Requests per Status (5m rate)",
      "type": "timeseries"
    },
    {
      "datasource": {
        "type": "prometheus",
        "uid": "Prometheus"
      },
      "fieldConfig": {
        "defaults": {
          "color": {
            "mode": "palette-classic"
          },
          "mappings": [],
          "thresholds": {
            "mode": "absolute",
            "steps": [
              {
                "color": "green",
                "value": null
              },
              {
                "color": "red",
                "value": 80
              }
            ]
          }
        },
        "overrides": []
      },
      "gridPos": {
        "h": 8,
        "w": 12,
        "x": 12,
        "y": 0
      },
      "id": 2,
      "options": {
        "legend": {
          "calcs": [],
          "displayMode": "list",
          "placement": "bottom"
        },
        "tooltip": {
          "mode": "single"
        }
      },
      "targets": [
        {
          "expr": "sum(rate(app_user_operations_total[5m]))",
          "legendFormat": "Ops/min",
          "refId": "A"
        }
      ],
      "title": "User Operations (5m rate)",
      "type": "timeseries"
    },
    {
      "datasource": {
        "type": "prometheus",
        "uid": "Prometheus"
      },
      "gridPos": {
        "h": 8,
        "w": 12,
        "x": 0,
        "y": 8
      },
      "id": 3,
      "options": {
        "legend": {
          "displayMode": "list",
          "placement": "right"
        },
        "tooltip": {
          "mode": "multi"
        }
      },
      "targets": [
        {
          "expr": "sum(app_user_operations_total) by (operation, outcome)",
          "legendFormat": "{{operation}} ({{outcome}})",
          "refId": "A"
        }
      ],
      "title": "User Operations Totals",
      "type": "timeseries"
    },
    {
      "datasource": {
        "type": "prometheus",
        "uid": "Prometheus"
      },
      "fieldConfig": {
        "defaults": {
          "unit": "s"
        },
        "overrides": []
      },
      "gridPos": {
        "h": 8,
        "w": 12,
        "x": 12,
        "y": 8
      },
      "id": 4,
      "options": {
        "legend": {
          "displayMode": "list",
          "placement": "bottom"
        },
        "tooltip": {
          "mode": "multi"
        }
      },
      "targets": [
        {
          "expr": "histogram_quantile(0.95, sum(rate(axum_http_requests_duration_seconds_bucket[5m])) by (le))",
          "legendFormat": "p95 latency",
          "refId": "A"
        }
      ],
      "title": "HTTP Latency p95 (5m)",
      "type": "timeseries"
    }
  ],
  "schemaVersion": 39,
  "style": "dark",
  "tags": [
    "webrust"
  ],
  "templating": {
    "list": []
  },
  "time": {
    "from": "now-1h",
    "to": "now"
  },
  "timepicker": {},
  "timezone": "",
  "title": "WebRust Overview",
  "uid": "webrust-overview",
  "version": 1
}
